cryptonet/__init__.py
cryptonet/main.py
cryptonet/matrix.py
cryptonetwork-0.0.4.dist-info/LICENSE
cryptonetwork-0.0.4.dist-info/METADATA
cryptonetwork-0.0.4.dist-info/WHEEL
cryptonetwork-0.0.4.dist-info/top_level.txt
cryptonetwork-0.0.4.dist-info/RECORD
