Metadata-Version: 2.1
Name: cryptonetwork
Version: 0.0.4
Summary: Package to learn efficiently about cryptography
Home-page: https://github.com/
Author: cryptonetwork
Author-email: author@example.com
Project-URL: Bug Tracker, https://github.com/
Classifier: Programming Language :: Python :: 3
Classifier: License :: OSI Approved :: MIT License
Classifier: Operating System :: OS Independent
Requires-Python: >=3.6
License-File: LICENSE
